seisio/__init__.py
seisio/_ibm2ieee.py
seisio/_txtheader.py
seisio/reader.py
seisio/seg2.py
seisio/segy.py
seisio/seisio.py
seisio/su.py
seisio/tools.py
seisio/writer.py
seisio/json/segy_binaryheader.json
seisio/json/segy_traceheader.json
seisio/json/segy_traceheader_ext1.json
seisio/json/su_traceheader.json
seisio-1.4.0.dist-info/licenses/LICENSE.md
seisio-1.4.0.dist-info/METADATA
seisio-1.4.0.dist-info/WHEEL
seisio-1.4.0.dist-info/top_level.txt
seisio-1.4.0.dist-info/RECORD
