Metadata-Version: 2.4
Name: seisio
Version: 1.4.0
Summary: I/O of seismic data
Author-email: Thomas Hertweck <geophysics@email.de>
Maintainer-email: Thomas Hertweck <geophysics@email.de>
License-Expression: LGPL-3.0-or-later
Project-URL: Repository, https://gitlab.kit.edu/thomas.hertweck/seisio
Keywords: seismic,SU,SEGY,SEG-Y,SEG2,I/O,read,write,radar,GPR
Classifier: Programming Language :: Python :: 3
Classifier: Operating System :: OS Independent
Requires-Python: >=3.10
License-File: LICENSE.md
Requires-Dist: numpy
Requires-Dist: pandas
Requires-Dist: numba
Provides-Extra: opt
Requires-Dist: tabulate; extra == "opt"
Dynamic: license-file
